<Color>
	<B>
		<double value="130" />
	</B>
	<G>
		<double value="130" />
	</G>
	<R>
		<double value="130" />
	</R>
</Color>
<CreationDate value="Fri Aug 01 08:39:49 2014"/>
<DynamicsOptions/>
<DynamicsType value="SimpleFreeMovement"/>
<FeatureSets>
	<fd1406851828 value=""/>
</FeatureSets>
<Info value="Unknown type, everything that is not of any known sort, can be used as a second type for classification reasons."/>
<Name value="Unknown Type"/>
<PreferredClassifierType value="CvBoost"/>
<type_likelihood_function>
	<d000>
		<double value="0.00" />
	</d000>
	<d001>
		<double value="0.05" />
	</d001>
	<d002>
		<double value="0.10" />
	</d002>
	<d003>
		<double value="0.15" />
	</d003>
	<d004>
		<double value="0.20" />
	</d004>
	<d005>
		<double value="0.25" />
	</d005>
	<d006>
		<double value="0.30" />
	</d006>
	<d007>
		<double value="0.35" />
	</d007>
	<d008>
		<double value="0.40" />
	</d008>
	<d009>
		<double value="0.45" />
	</d009>
	<d010>
		<double value="0.50" />
	</d010>
	<d011>
		<double value="0.55" />
	</d011>
	<d012>
		<double value="0.60" />
	</d012>
	<d013>
		<double value="0.65" />
	</d013>
	<d014>
		<double value="0.70" />
	</d014>
	<d015>
		<double value="0.75" />
	</d015>
	<d016>
		<double value="0.80" />
	</d016>
	<d017>
		<double value="0.85" />
	</d017>
	<d018>
		<double value="0.90" />
	</d018>
	<d019>
		<double value="0.95" />
	</d019>
	<d020>
		<double value="1.00" />
	</d020>
</type_likelihood_function>

